controller/__init__.py
payall/__init__.py
payall/__main__.py
solanaprocessor/__init__.py
payall-1.0.2.3.dist-info/LICENSE
payall-1.0.2.3.dist-info/METADATA
payall-1.0.2.3.dist-info/WHEEL
payall-1.0.2.3.dist-info/entry_points.txt
payall-1.0.2.3.dist-info/top_level.txt
payall-1.0.2.3.dist-info/RECORD
